{
    "key": "group_624e1642c1806",
    "title": "[CLONE] Screen",
    "fields": [
        {
            "key": "field_624ce03729fc6",
            "label": "screen",
            "name": "screen",
            "type": "group",
            "instructions": "",
            "required": 0,
            "conditional_logic": 0,
            "wrapper": {
                "width": "",
                "class": "",
                "id": ""
            },
            "acfe_save_meta": 0,
            "layout": "block",
            "acfe_seamless_style": 1,
            "acfe_group_modal": 0,
            "sub_fields": [
                {
                    "key": "field_625c8c415ffac",
                    "label": "Configure screen",
                    "name": "configured",
                    "type": "true_false",
                    "instructions": "Turning this off will disable all customizations for this screen size, <strong>including automatic sizing<\/strong> in raster images that might be set as the background. \r\n\r\nIt's usually better to unselect any options you might've selected. If you're looking to remove visual clutter while you edit, close the accordion instead.",
                    "required": 0,
                    "conditional_logic": 0,
                    "wrapper": {
                        "width": "",
                        "class": "",
                        "id": ""
                    },
                    "acfe_save_meta": 0,
                    "message": "",
                    "default_value": 1,
                    "ui": 1,
                    "ui_on_text": "",
                    "ui_off_text": ""
                },
                {
                    "key": "field_625c8e2eabff3",
                    "label": "Size",
                    "name": "",
                    "type": "accordion",
                    "instructions": "",
                    "required": 0,
                    "conditional_logic": [
                        [
                            {
                                "field": "field_625c8c415ffac",
                                "operator": "==",
                                "value": "1"
                            }
                        ]
                    ],
                    "wrapper": {
                        "width": "",
                        "class": "",
                        "id": ""
                    },
                    "open": 0,
                    "multi_expand": 1,
                    "endpoint": 0
                },
                {
                    "key": "field_625c9b9a46111",
                    "label": "Shrink",
                    "name": "flex-shrink",
                    "type": "button_group",
                    "instructions": "Allows item to shrink in size if other elements require space.",
                    "required": 0,
                    "conditional_logic": [
                        [
                            {
                                "field": "field_625c8c415ffac",
                                "operator": "==",
                                "value": "1"
                            }
                        ]
                    ],
                    "wrapper": {
                        "width": "33.3",
                        "class": "",
                        "id": ""
                    },
                    "acfe_save_meta": 0,
                    "choices": {
                        "shrink": "Shrink",
                        "shrink-0": "No shrink"
                    },
                    "allow_null": 1,
                    "default_value": "",
                    "layout": "horizontal",
                    "return_format": "value"
                },
                {
                    "key": "field_625c9bd646112",
                    "label": "Grow",
                    "name": "flex-grow",
                    "type": "button_group",
                    "instructions": "Allows item to grow in size if it requires space.",
                    "required": 0,
                    "conditional_logic": [
                        [
                            {
                                "field": "field_625c8c415ffac",
                                "operator": "==",
                                "value": "1"
                            }
                        ]
                    ],
                    "wrapper": {
                        "width": "33.3",
                        "class": "",
                        "id": ""
                    },
                    "acfe_save_meta": 0,
                    "choices": {
                        "grow": "Grow",
                        "grow-0": "No grow"
                    },
                    "allow_null": 1,
                    "default_value": "",
                    "layout": "horizontal",
                    "return_format": "value"
                },
                {
                    "key": "field_624ce04729fc7",
                    "label": "Width",
                    "name": "width",
                    "type": "button_group",
                    "instructions": "Determines how much space the element will take.",
                    "required": 0,
                    "conditional_logic": [
                        [
                            {
                                "field": "field_625c8c415ffac",
                                "operator": "==",
                                "value": "1"
                            }
                        ]
                    ],
                    "wrapper": {
                        "width": "33.3",
                        "class": "",
                        "id": ""
                    },
                    "acfe_save_meta": 0,
                    "choices": {
                        "w-1\/1": "1\/1",
                        "w-1\/2": "1\/2",
                        "w-1\/3": "1\/3",
                        "w-2\/3": "2\/3",
                        "w-1\/4": "1\/4",
                        "w-2\/4": "2\/4",
                        "w-3\/4": "3\/4",
                        "w-1\/5": "1\/5",
                        "w-2\/5": "2\/5",
                        "w-3\/5": "3\/5",
                        "w-4\/5": "4\/5"
                    },
                    "allow_null": 1,
                    "default_value": "",
                    "layout": "vertical",
                    "return_format": "value"
                },
                {
                    "key": "field_625c9671f235d",
                    "label": "Padding",
                    "name": "padding",
                    "type": "group",
                    "instructions": "",
                    "required": 0,
                    "conditional_logic": [
                        [
                            {
                                "field": "field_625c8c415ffac",
                                "operator": "==",
                                "value": "1"
                            }
                        ]
                    ],
                    "wrapper": {
                        "width": "50",
                        "class": "",
                        "id": ""
                    },
                    "acfe_save_meta": 0,
                    "layout": "block",
                    "acfe_seamless_style": 1,
                    "acfe_group_modal": 0,
                    "sub_fields": [
                        {
                            "key": "field_625c9671f235e",
                            "label": "Top",
                            "name": "top",
                            "type": "button_group",
                            "instructions": "",
                            "required": 0,
                            "conditional_logic": 0,
                            "wrapper": {
                                "width": "40",
                                "class": "",
                                "id": ""
                            },
                            "acfe_save_meta": 0,
                            "choices": {
                                "auto": "auto",
                                "0": "0",
                                "1": "1",
                                "2": "2",
                                "3": "3",
                                "4": "4",
                                "5": "5",
                                "6": "6",
                                "7": "7",
                                "8": "8",
                                "9": "9",
                                "10": "10"
                            },
                            "allow_null": 1,
                            "default_value": "",
                            "layout": "vertical",
                            "return_format": "value"
                        },
                        {
                            "key": "field_625c9671f235f",
                            "label": "Bottom",
                            "name": "bottom",
                            "type": "button_group",
                            "instructions": "",
                            "required": 0,
                            "conditional_logic": [
                                [
                                    {
                                        "field": "field_625c9671f2361",
                                        "operator": "!=",
                                        "value": "1"
                                    }
                                ]
                            ],
                            "wrapper": {
                                "width": "40",
                                "class": "",
                                "id": ""
                            },
                            "acfe_save_meta": 0,
                            "choices": {
                                "auto": "auto",
                                "0": "0",
                                "1": "1",
                                "2": "2",
                                "3": "3",
                                "4": "4",
                                "5": "5",
                                "6": "6",
                                "7": "7",
                                "8": "8",
                                "9": "9",
                                "10": "10"
                            },
                            "allow_null": 1,
                            "default_value": "",
                            "layout": "vertical",
                            "return_format": "value"
                        },
                        {
                            "key": "field_625c9671f2360",
                            "label": "Bottom",
                            "name": "",
                            "type": "message",
                            "instructions": "",
                            "required": 0,
                            "conditional_logic": [
                                [
                                    {
                                        "field": "field_625c9671f2361",
                                        "operator": "==",
                                        "value": "1"
                                    }
                                ]
                            ],
                            "wrapper": {
                                "width": "40",
                                "class": "",
                                "id": ""
                            },
                            "message": "Bottom value is the same as top value.",
                            "new_lines": "wpautop",
                            "esc_html": 0
                        },
                        {
                            "key": "field_625c9671f2361",
                            "label": "Use top as bottom",
                            "name": "topOnBottom",
                            "type": "true_false",
                            "instructions": "",
                            "required": 0,
                            "conditional_logic": 0,
                            "wrapper": {
                                "width": "20",
                                "class": "",
                                "id": ""
                            },
                            "acfe_save_meta": 0,
                            "message": "",
                            "default_value": 1,
                            "ui": 1,
                            "ui_on_text": "",
                            "ui_off_text": ""
                        },
                        {
                            "key": "field_625c9671f2362",
                            "label": "Left",
                            "name": "left",
                            "type": "button_group",
                            "instructions": "",
                            "required": 0,
                            "conditional_logic": 0,
                            "wrapper": {
                                "width": "40",
                                "class": "",
                                "id": ""
                            },
                            "acfe_save_meta": 0,
                            "choices": {
                                "auto": "auto",
                                "0": "0",
                                "1": "1",
                                "2": "2",
                                "3": "3",
                                "4": "4",
                                "5": "5",
                                "6": "6",
                                "7": "7",
                                "8": "8",
                                "9": "9",
                                "10": "10"
                            },
                            "allow_null": 1,
                            "default_value": "",
                            "layout": "vertical",
                            "return_format": "value"
                        },
                        {
                            "key": "field_625c9671f2363",
                            "label": "Right",
                            "name": "right",
                            "type": "button_group",
                            "instructions": "",
                            "required": 0,
                            "conditional_logic": [
                                [
                                    {
                                        "field": "field_625c9671f2365",
                                        "operator": "!=",
                                        "value": "1"
                                    }
                                ]
                            ],
                            "wrapper": {
                                "width": "40",
                                "class": "",
                                "id": ""
                            },
                            "acfe_save_meta": 0,
                            "choices": {
                                "auto": "auto",
                                "0": "0",
                                "1": "1",
                                "2": "2",
                                "3": "3",
                                "4": "4",
                                "5": "5",
                                "6": "6",
                                "7": "7",
                                "8": "8",
                                "9": "9",
                                "10": "10"
                            },
                            "allow_null": 1,
                            "default_value": "",
                            "layout": "vertical",
                            "return_format": "value"
                        },
                        {
                            "key": "field_625c9671f2364",
                            "label": "Right",
                            "name": "",
                            "type": "message",
                            "instructions": "",
                            "required": 0,
                            "conditional_logic": [
                                [
                                    {
                                        "field": "field_625c9671f2365",
                                        "operator": "==",
                                        "value": "1"
                                    }
                                ]
                            ],
                            "wrapper": {
                                "width": "40",
                                "class": "",
                                "id": ""
                            },
                            "message": "Right value is the same as left value.",
                            "new_lines": "wpautop",
                            "esc_html": 0
                        },
                        {
                            "key": "field_625c9671f2365",
                            "label": "Use left as right",
                            "name": "leftOnRight",
                            "type": "true_false",
                            "instructions": "",
                            "required": 0,
                            "conditional_logic": 0,
                            "wrapper": {
                                "width": "20",
                                "class": "",
                                "id": ""
                            },
                            "acfe_save_meta": 0,
                            "message": "",
                            "default_value": 1,
                            "ui": 1,
                            "ui_on_text": "",
                            "ui_off_text": ""
                        }
                    ]
                },
                {
                    "key": "field_6249f930c4ee0",
                    "label": "Margin",
                    "name": "margin",
                    "type": "group",
                    "instructions": "",
                    "required": 0,
                    "conditional_logic": [
                        [
                            {
                                "field": "field_625c8c415ffac",
                                "operator": "==",
                                "value": "1"
                            }
                        ]
                    ],
                    "wrapper": {
                        "width": "50",
                        "class": "",
                        "id": ""
                    },
                    "acfe_save_meta": 0,
                    "layout": "block",
                    "acfe_seamless_style": 1,
                    "acfe_group_modal": 0,
                    "sub_fields": [
                        {
                            "key": "field_624ccbcfe7872",
                            "label": "Top",
                            "name": "top",
                            "type": "button_group",
                            "instructions": "",
                            "required": 0,
                            "conditional_logic": 0,
                            "wrapper": {
                                "width": "40",
                                "class": "",
                                "id": ""
                            },
                            "acfe_save_meta": 0,
                            "choices": {
                                "auto": "auto",
                                "0": "0",
                                "1": "1",
                                "2": "2",
                                "3": "3",
                                "4": "4",
                                "5": "5",
                                "6": "6",
                                "7": "7",
                                "8": "8",
                                "9": "9",
                                "10": "10"
                            },
                            "allow_null": 1,
                            "default_value": "",
                            "layout": "vertical",
                            "return_format": "value"
                        },
                        {
                            "key": "field_624ccdf92ad23",
                            "label": "Bottom",
                            "name": "bottom",
                            "type": "button_group",
                            "instructions": "",
                            "required": 0,
                            "conditional_logic": [
                                [
                                    {
                                        "field": "field_624ccdcc2ad22",
                                        "operator": "!=",
                                        "value": "1"
                                    }
                                ]
                            ],
                            "wrapper": {
                                "width": "40",
                                "class": "",
                                "id": ""
                            },
                            "choices": {
                                "auto": "auto",
                                "0": "0",
                                "1": "1",
                                "2": "2",
                                "3": "3",
                                "4": "4",
                                "5": "5",
                                "6": "6",
                                "7": "7",
                                "8": "8",
                                "9": "9",
                                "10": "10"
                            },
                            "allow_null": 1,
                            "default_value": "",
                            "layout": "vertical",
                            "return_format": "value"
                        },
                        {
                            "key": "field_625c946ca678f",
                            "label": "Bottom",
                            "name": "",
                            "type": "message",
                            "instructions": "",
                            "required": 0,
                            "conditional_logic": [
                                [
                                    {
                                        "field": "field_624ccdcc2ad22",
                                        "operator": "==",
                                        "value": "1"
                                    }
                                ]
                            ],
                            "wrapper": {
                                "width": "40",
                                "class": "",
                                "id": ""
                            },
                            "message": "Bottom value is the same as top value.",
                            "new_lines": "wpautop",
                            "esc_html": 0
                        },
                        {
                            "key": "field_624ccdcc2ad22",
                            "label": "Use top as bottom",
                            "name": "topOnBottom",
                            "type": "true_false",
                            "instructions": "",
                            "required": 0,
                            "conditional_logic": 0,
                            "wrapper": {
                                "width": "20",
                                "class": "",
                                "id": ""
                            },
                            "acfe_save_meta": 0,
                            "message": "",
                            "default_value": 1,
                            "ui": 1,
                            "ui_on_text": "",
                            "ui_off_text": ""
                        },
                        {
                            "key": "field_624cce96c2192",
                            "label": "Left",
                            "name": "left",
                            "type": "button_group",
                            "instructions": "",
                            "required": 0,
                            "conditional_logic": 0,
                            "wrapper": {
                                "width": "40",
                                "class": "",
                                "id": ""
                            },
                            "choices": {
                                "auto": "auto",
                                "0": "0",
                                "1": "1",
                                "2": "2",
                                "3": "3",
                                "4": "4",
                                "5": "5",
                                "6": "6",
                                "7": "7",
                                "8": "8",
                                "9": "9",
                                "10": "10"
                            },
                            "allow_null": 1,
                            "default_value": "",
                            "layout": "vertical",
                            "return_format": "value"
                        },
                        {
                            "key": "field_624ccea6c2193",
                            "label": "Right",
                            "name": "right",
                            "type": "button_group",
                            "instructions": "",
                            "required": 0,
                            "conditional_logic": [
                                [
                                    {
                                        "field": "field_624cce78c2191",
                                        "operator": "!=",
                                        "value": "1"
                                    }
                                ]
                            ],
                            "wrapper": {
                                "width": "40",
                                "class": "",
                                "id": ""
                            },
                            "choices": {
                                "auto": "auto",
                                "0": "0",
                                "1": "1",
                                "2": "2",
                                "3": "3",
                                "4": "4",
                                "5": "5",
                                "6": "6",
                                "7": "7",
                                "8": "8",
                                "9": "9",
                                "10": "10"
                            },
                            "allow_null": 1,
                            "default_value": "",
                            "layout": "vertical",
                            "return_format": "value"
                        },
                        {
                            "key": "field_625c949da6790",
                            "label": "Right",
                            "name": "",
                            "type": "message",
                            "instructions": "",
                            "required": 0,
                            "conditional_logic": [
                                [
                                    {
                                        "field": "field_624cce78c2191",
                                        "operator": "==",
                                        "value": "1"
                                    }
                                ]
                            ],
                            "wrapper": {
                                "width": "40",
                                "class": "",
                                "id": ""
                            },
                            "message": "Right value is the same as left value.",
                            "new_lines": "wpautop",
                            "esc_html": 0
                        },
                        {
                            "key": "field_624cce78c2191",
                            "label": "Use left as right",
                            "name": "leftOnRight",
                            "type": "true_false",
                            "instructions": "",
                            "required": 0,
                            "conditional_logic": 0,
                            "wrapper": {
                                "width": "20",
                                "class": "",
                                "id": ""
                            },
                            "acfe_save_meta": 0,
                            "message": "",
                            "default_value": 1,
                            "ui": 1,
                            "ui_on_text": "",
                            "ui_off_text": ""
                        }
                    ]
                },
                {
                    "key": "field_625c8ea7abff4",
                    "label": "Layout",
                    "name": "",
                    "type": "accordion",
                    "instructions": "",
                    "required": 0,
                    "conditional_logic": [
                        [
                            {
                                "field": "field_625c8c415ffac",
                                "operator": "==",
                                "value": "1"
                            }
                        ]
                    ],
                    "wrapper": {
                        "width": "",
                        "class": "",
                        "id": ""
                    },
                    "open": 0,
                    "multi_expand": 1,
                    "endpoint": 0
                },
                {
                    "key": "field_625dfed13d2f9",
                    "label": "Display",
                    "name": "display",
                    "type": "button_group",
                    "instructions": "Selecting Hidden will hide the element in this screen size. If you want to show it again in another screen size, you need to configure that screen size separately.",
                    "required": 0,
                    "conditional_logic": 0,
                    "wrapper": {
                        "width": "33.3",
                        "class": "",
                        "id": ""
                    },
                    "acfe_save_meta": 0,
                    "choices": {
                        "hidden": "Hidden",
                        "flex": "Flex"
                    },
                    "allow_null": 1,
                    "default_value": "",
                    "layout": "horizontal",
                    "return_format": "value"
                },
                {
                    "key": "field_626eb8d1a50e8",
                    "label": "Text align",
                    "name": "textAlign",
                    "type": "button_group",
                    "instructions": "",
                    "required": 0,
                    "conditional_logic": 0,
                    "wrapper": {
                        "width": "",
                        "class": "",
                        "id": ""
                    },
                    "choices": {
                        "text-left": "Left",
                        "text-center": "Center",
                        "text-right": "Right",
                        "text-justify": "Justify"
                    },
                    "allow_null": 1,
                    "default_value": "",
                    "layout": "horizontal",
                    "return_format": "value"
                },
                {
                    "key": "field_625c9b5a46110",
                    "label": "Wrap",
                    "name": "flex-wrap",
                    "type": "button_group",
                    "instructions": "Turning off wrapping forces items to stay on the same line even if they don't fit. Making no selection here is the same as choosing Wrap.",
                    "required": 0,
                    "conditional_logic": [
                        [
                            {
                                "field": "field_625c8c415ffac",
                                "operator": "==",
                                "value": "1"
                            }
                        ]
                    ],
                    "wrapper": {
                        "width": "33.3",
                        "class": "",
                        "id": ""
                    },
                    "acfe_save_meta": 0,
                    "choices": {
                        "flex-wrap": "Wrap",
                        "flex-wrap-reverse": "Wrap reverse",
                        "flex-nowrap": "No wrap"
                    },
                    "allow_null": 1,
                    "default_value": "",
                    "layout": "horizontal",
                    "return_format": "value"
                },
                {
                    "key": "field_6249d42c7aeb7",
                    "label": "Align",
                    "name": "align",
                    "type": "button_group",
                    "instructions": "",
                    "required": 0,
                    "conditional_logic": [
                        [
                            {
                                "field": "field_625c8c415ffac",
                                "operator": "==",
                                "value": "1"
                            }
                        ]
                    ],
                    "wrapper": {
                        "width": "33.3",
                        "class": "",
                        "id": ""
                    },
                    "acfe_save_meta": 0,
                    "choices": {
                        "items-start": "items-start",
                        "items-end": "items-end",
                        "items-center": "items-center",
                        "items-baseline": "items-baseline",
                        "items-stretch": "items-stretch"
                    },
                    "allow_null": 1,
                    "default_value": "",
                    "layout": "vertical",
                    "return_format": "value"
                },
                {
                    "key": "field_6249cd7401c1b",
                    "label": "Justification",
                    "name": "justify",
                    "type": "button_group",
                    "instructions": "",
                    "required": 0,
                    "conditional_logic": [
                        [
                            {
                                "field": "field_625c8c415ffac",
                                "operator": "==",
                                "value": "1"
                            }
                        ]
                    ],
                    "wrapper": {
                        "width": "33.3",
                        "class": "",
                        "id": ""
                    },
                    "acfe_save_meta": 0,
                    "choices": {
                        "justify-start": "justify-start",
                        "justify-end": "justify-end",
                        "justify-center": "justify-center",
                        "justify-between": "justify-between",
                        "justify-evenly": "justify-evenly"
                    },
                    "allow_null": 1,
                    "default_value": "",
                    "layout": "vertical",
                    "return_format": "value"
                },
                {
                    "key": "field_6249cef6e4c39",
                    "label": "Direction",
                    "name": "direction",
                    "type": "button_group",
                    "instructions": "",
                    "required": 0,
                    "conditional_logic": [
                        [
                            {
                                "field": "field_625c8c415ffac",
                                "operator": "==",
                                "value": "1"
                            }
                        ]
                    ],
                    "wrapper": {
                        "width": "33.3",
                        "class": "",
                        "id": ""
                    },
                    "acfe_save_meta": 0,
                    "choices": {
                        "flex-row": "flex-row",
                        "flex-row-reverse": "flex-row-reverse",
                        "flex-col": "flex-col",
                        "flex-col-reverse": "flex-col-reverse"
                    },
                    "allow_null": 1,
                    "default_value": "",
                    "layout": "vertical",
                    "return_format": "value"
                },
                {
                    "key": "field_625c8ebcabff5",
                    "label": "Background",
                    "name": "",
                    "type": "accordion",
                    "instructions": "",
                    "required": 0,
                    "conditional_logic": [
                        [
                            {
                                "field": "field_625c8c415ffac",
                                "operator": "==",
                                "value": "1"
                            }
                        ]
                    ],
                    "wrapper": {
                        "width": "",
                        "class": "",
                        "id": ""
                    },
                    "open": 0,
                    "multi_expand": 1,
                    "endpoint": 0
                },
                {
                    "key": "field_6249c61213eab",
                    "label": "Background",
                    "name": "background",
                    "type": "group",
                    "instructions": "",
                    "required": 0,
                    "conditional_logic": [
                        [
                            {
                                "field": "field_625c8c415ffac",
                                "operator": "==",
                                "value": "1"
                            }
                        ]
                    ],
                    "wrapper": {
                        "width": "",
                        "class": "",
                        "id": ""
                    },
                    "acfe_save_meta": 0,
                    "layout": "block",
                    "acfe_seamless_style": 0,
                    "acfe_group_modal": 0,
                    "sub_fields": [
                        {
                            "key": "field_626eb948a50e9",
                            "label": "Disable image",
                            "name": "disableImage",
                            "type": "true_false",
                            "instructions": "Disables the configured background image in this breakpoint. Useful if you're using a background image in mobile and a dedicated image block in desktop.",
                            "required": 0,
                            "conditional_logic": 0,
                            "wrapper": {
                                "width": "",
                                "class": "",
                                "id": ""
                            },
                            "message": "",
                            "default_value": 0,
                            "ui": 1,
                            "ui_on_text": "",
                            "ui_off_text": ""
                        },
                        {
                            "key": "field_6249c61813eac",
                            "label": "Image",
                            "name": "image",
                            "type": "image",
                            "instructions": "Prefer vector graphics (.SVG) over raster images (.PNG, .JPEG, etc.)",
                            "required": 0,
                            "conditional_logic": [
                                [
                                    {
                                        "field": "field_626eb948a50e9",
                                        "operator": "!=",
                                        "value": "1"
                                    }
                                ]
                            ],
                            "wrapper": {
                                "width": "50",
                                "class": "",
                                "id": ""
                            },
                            "acfe_save_meta": 0,
                            "uploader": "",
                            "acfe_thumbnail": 0,
                            "return_format": "array",
                            "preview_size": "medium",
                            "min_width": "",
                            "min_height": "",
                            "min_size": "",
                            "max_width": "",
                            "max_height": "",
                            "max_size": "",
                            "mime_types": "",
                            "library": "all"
                        },
                        {
                            "key": "field_624a070465be5",
                            "label": "Size",
                            "name": "size",
                            "type": "select",
                            "instructions": "Cover fills the entire element, discarding portions of the image if necessary. Contain ensures the image is always visible, at the cost of background covered. The other options? Try them. Do be aware of how the options behave at different screen sizes!",
                            "required": 0,
                            "conditional_logic": [
                                [
                                    {
                                        "field": "field_626eb948a50e9",
                                        "operator": "!=",
                                        "value": "1"
                                    }
                                ]
                            ],
                            "wrapper": {
                                "width": "50",
                                "class": "",
                                "id": ""
                            },
                            "acfe_save_meta": 0,
                            "choices": {
                                "bg-cover": "Cover",
                                "bg-contain": "Contain",
                                "bg-auto": "Auto",
                                "bg-100-100": "Scaling SVG",
                                "bg-400": "400px"
                            },
                            "default_value": false,
                            "allow_null": 1,
                            "multiple": 0,
                            "ui": 0,
                            "return_format": "value",
                            "placeholder": "",
                            "ajax": 0
                        },
                        {
                            "key": "field_624a074665be6",
                            "label": "Position",
                            "name": "position",
                            "type": "button_group",
                            "instructions": "",
                            "required": 0,
                            "conditional_logic": [
                                [
                                    {
                                        "field": "field_626eb948a50e9",
                                        "operator": "!=",
                                        "value": "1"
                                    }
                                ]
                            ],
                            "wrapper": {
                                "width": "50",
                                "class": "",
                                "id": ""
                            },
                            "acfe_save_meta": 0,
                            "choices": {
                                "leftTop": "Left top",
                                "centerTop": "Center top",
                                "rightTop": "Right top",
                                "leftCenter": "Left center",
                                "centerCenter": "Center center",
                                "rightCenter": "Right center",
                                "leftBottom": "Left bottom",
                                "centerBottom": "Center bottom",
                                "rightBottom": "Right bottom"
                            },
                            "allow_null": 1,
                            "default_value": "",
                            "layout": "vertical",
                            "return_format": "value"
                        },
                        {
                            "key": "field_624b55e816486",
                            "label": "Colour",
                            "name": "colour",
                            "type": "button_group",
                            "instructions": "",
                            "required": 0,
                            "conditional_logic": 0,
                            "wrapper": {
                                "width": "50",
                                "class": "",
                                "id": ""
                            },
                            "acfe_save_meta": 0,
                            "choices": {
                                "bg-brand": "Brand",
                                "bg-white": "White",
                                "bg-black": "Black",
                                "bg-cyan": "Cyan",
                                "bg-orange": "Orange",
                                "bg-gray-100": "Gray",
                                "bg-transparent": "Transparent",
                                "glass": "Glass"
                            },
                            "allow_null": 1,
                            "default_value": "",
                            "layout": "vertical",
                            "return_format": "value"
                        }
                    ]
                },
                {
                    "key": "field_626ee57dcd460",
                    "label": "Text color",
                    "name": "textColor",
                    "type": "button_group",
                    "instructions": "",
                    "required": 0,
                    "conditional_logic": 0,
                    "wrapper": {
                        "width": "",
                        "class": "",
                        "id": ""
                    },
                    "acfe_save_meta": 0,
                    "choices": {
                        "text-brand": "Brand",
                        "text-white": "White",
                        "text-black": "Black",
                        "text-cyan": "Cyan",
                        "text-orange": "Orange",
                        "text-gray-100": "Gray"
                    },
                    "allow_null": 1,
                    "default_value": "",
                    "layout": "horizontal",
                    "return_format": "value"
                }
            ]
        }
    ],
    "location": [
        [
            {
                "param": "post_type",
                "operator": "==",
                "value": "post"
            }
        ]
    ],
    "menu_order": 0,
    "position": "normal",
    "style": "default",
    "label_placement": "left",
    "instruction_placement": "label",
    "hide_on_screen": "",
    "active": false,
    "description": "",
    "show_in_rest": 0,
    "acfe_display_title": "",
    "acfe_autosync": [
        "json"
    ],
    "acfe_form": 0,
    "acfe_meta": "",
    "acfe_note": "",
    "modified": 1651617326
}